nimp/VERSION
nimp/__init__.py
nimp/__main__.py
nimp/artifacts.py
nimp/build.py
nimp/command.py
nimp/environment.py
nimp/exceptions.py
nimp/nimp_cli.py
nimp/summary.py
nimp/symstore.py
nimp/system.py
nimp/unreal.py
nimp/base_commands/__init__.py
nimp/base_commands/automation.py
nimp/base_commands/build.py
nimp/base_commands/check.py
nimp/base_commands/commandlet.py
nimp/base_commands/create_loadlist.py
nimp/base_commands/dev.py
nimp/base_commands/download_fileset.py
nimp/base_commands/fileset.py
nimp/base_commands/p4.py
nimp/base_commands/package.py
nimp/base_commands/run.py
nimp/base_commands/run_legacy.py
nimp/base_commands/symbol_server.py
nimp/base_commands/update_symbol_server.py
nimp/base_commands/upload.py
nimp/base_commands/upload_fileset.py
nimp/base_platforms/__init__.py
nimp/base_platforms/android.py
nimp/base_platforms/basegdk.py
nimp/base_platforms/desktop.py
nimp/base_platforms/ios.py
nimp/base_platforms/ps4.py
nimp/base_platforms/ps5.py
nimp/base_platforms/switch.py
nimp/base_platforms/wingdk.py
nimp/base_platforms/xboxone.py
nimp/base_platforms/xsx.py
nimp/model/__init__.py
nimp/model/jira.py
nimp/model/symbol_server.py
nimp/sys/__init__.py
nimp/sys/logging.py
nimp/sys/platform.py
nimp/sys/process.py
nimp/unreal_engine/__init__.py
nimp/unreal_engine/build.py
nimp/utils/__init__.py
nimp/utils/git.py
nimp/utils/p4.py
nimp/utils/profiling.py
nimp/utils/python.py
nimp/utils/version.py
nimp_cli-0.16.22.dist-info/licenses/LICENSE
nimp_cli-0.16.22.dist-info/METADATA
nimp_cli-0.16.22.dist-info/WHEEL
nimp_cli-0.16.22.dist-info/entry_points.txt
nimp_cli-0.16.22.dist-info/top_level.txt
nimp_cli-0.16.22.dist-info/RECORD
