Metadata-Version: 2.4
Name: nimp-cli
Version: 0.16.22
Summary: Multipurpose build tool
Author-email: Dontnod Entertainment <root@dont-nod.com>
License: MIT License
Project-URL: Repository, https://github.com/dontnod/nimp
Keywords: build,compile,unrealengine
Classifier: Development Status :: 3 - Alpha
Classifier: Environment :: Console
Classifier: Intended Audience :: Developers
Classifier: License :: OSI Approved :: MIT License
Classifier: Operating System :: OS Independent
Classifier: Operating System :: MacOS
Classifier: Operating System :: Microsoft :: Windows
Classifier: Operating System :: POSIX
Classifier: Operating System :: Unix
Classifier: Programming Language :: Python :: 3
Classifier: Topic :: Software Development :: Build Tools
Requires-Python: >=3.9
License-File: LICENSE
Requires-Dist: rich
Requires-Dist: glob2
Requires-Dist: packaging
Requires-Dist: python-magic
Requires-Dist: requests
Requires-Dist: giteapy
Requires-Dist: jira
Requires-Dist: psutil>=6.1.0
Provides-Extra: torrent
Requires-Dist: torf>=4.3.0; extra == "torrent"
Provides-Extra: dev
Requires-Dist: ruff==0.11.3; extra == "dev"
Requires-Dist: pylint==3.2.6; extra == "dev"
Dynamic: license-file
